cgmac/__init__.py
cgmac/cgmac.py
cgmac-0.1.0.dist-info/LICENSE.txt
cgmac-0.1.0.dist-info/METADATA
cgmac-0.1.0.dist-info/WHEEL
cgmac-0.1.0.dist-info/top_level.txt
cgmac-0.1.0.dist-info/RECORD
