Metadata-Version: 2.1
Name: cgmac
Version: 0.1.0
Summary: Calculate CGM-derived measures
Home-page: https://github.com/HikaruSugimoto/cgmac
Author: Hikaru Sugimoto
Author-email: sugimoto.hikaru14@gmail.com
Maintainer: Hikaru Sugimoto
Maintainer-email: sugimoto.hikaru14@gmail.com
License: The software is provided under a modified Apache License Version 2.0.
Platform: UNKNOWN
License-File: LICENSE.txt
Requires-Dist: pandas<=2.2.3
Requires-Dist: numpy<=1.26.4
Requires-Dist: statsmodels<=0.14.4
